SmartNlp/__init__.py
SmartNlp/core.py
smart_nlp_package-0.2.0.dist-info/licenses/LICENSE
smart_nlp_package-0.2.0.dist-info/METADATA
smart_nlp_package-0.2.0.dist-info/WHEEL
smart_nlp_package-0.2.0.dist-info/top_level.txt
smart_nlp_package-0.2.0.dist-info/RECORD
