Metadata-Version: 2.4
Name: smart-nlp-package
Version: 0.2.0
Summary: NLP, A smart utility package for fuzzy matching and deep JSON search.
Home-page: https://github.com/yogesh517/smart-nlp-package
Author: Yogesh Vyas
Author-email: yogesh vyas <vyasyogesh517@gmail.com>
License: MIT License
Keywords: nlp,fuzzy-match,json-search
Classifier: Programming Language :: Python :: 3
Classifier: License :: OSI Approved :: MIT License
Requires-Python: >=3.10
License-File: LICENSE
Dynamic: author
Dynamic: home-page
Dynamic: license-file
Dynamic: requires-python
